{
  "name": "ButtonGroup",
  "type": "component",
  "filePath": "src/components/ui/ButtonGroup.astro",
  "description": "ButtonGroup Component",
  "props": {
    "variant": {
      "type": "'default' | 'outline'",
      "optional": true,
      "default": "'default'"
    },
    "size": {
      "type": "'sm' | 'md' | 'lg'",
      "optional": true,
      "default": "'md'"
    },
    "orientation": {
      "type": "'horizontal' | 'vertical'",
      "optional": true,
      "default": "'horizontal'"
    },
    "class": {
      "type": "string",
      "optional": true,
      "default": "''"
    }
  },
  "defaults": {
    "theme": "cp",
    "mode": "light",
    "variant": "'default'",
    "size": "'md'"
  },
  "specs": {
    "default-cp-light-sm": {
      "_meta": {
        "theme": "cp",
        "mode": "light",
        "locked": true
      },
      "_buildContract": {
        "criticalSelectors": {
          ".btn-group": {}
        },
        "forbiddenModifications": [
          "Do not use Tailwind arbitrary values",
          "Do not change hex colors to named colors",
          "Do not simplify box-shadow values",
          "Do not add CSS properties that are not in criticalSelectors or in elements[].styles (or element states)",
          "Do not reorder children: follow contentOrder and elements[].children order exactly",
          "Build exactly what is in the spec: structure, styles, and defaultContent from the JSON only; no inference, no additions, no \"fixes\""
        ]
      },
      "elements": [
        {
          "selector": ".btn-group",
          "tag": "div",
          "styles": {}
        }
      ]
    },
    "default-cp-light-md": {
      "_meta": {
        "theme": "cp",
        "mode": "light",
        "locked": true
      },
      "_buildContract": {
        "criticalSelectors": {
          ".btn-group": {}
        },
        "forbiddenModifications": [
          "Do not use Tailwind arbitrary values",
          "Do not change hex colors to named colors",
          "Do not simplify box-shadow values",
          "Do not add CSS properties that are not in criticalSelectors or in elements[].styles (or element states)",
          "Do not reorder children: follow contentOrder and elements[].children order exactly",
          "Build exactly what is in the spec: structure, styles, and defaultContent from the JSON only; no inference, no additions, no \"fixes\""
        ]
      },
      "elements": [
        {
          "selector": ".btn-group",
          "tag": "div",
          "styles": {}
        }
      ]
    },
    "default-cp-light-lg": {
      "_meta": {
        "theme": "cp",
        "mode": "light",
        "locked": true
      },
      "_buildContract": {
        "criticalSelectors": {
          ".btn-group": {}
        },
        "forbiddenModifications": [
          "Do not use Tailwind arbitrary values",
          "Do not change hex colors to named colors",
          "Do not simplify box-shadow values",
          "Do not add CSS properties that are not in criticalSelectors or in elements[].styles (or element states)",
          "Do not reorder children: follow contentOrder and elements[].children order exactly",
          "Build exactly what is in the spec: structure, styles, and defaultContent from the JSON only; no inference, no additions, no \"fixes\""
        ]
      },
      "elements": [
        {
          "selector": ".btn-group",
          "tag": "div",
          "styles": {}
        }
      ]
    },
    "default-cp-dark-sm": {
      "_meta": {
        "theme": "cp",
        "mode": "dark",
        "locked": true
      },
      "_buildContract": {
        "criticalSelectors": {
          ".btn-group": {}
        },
        "forbiddenModifications": [
          "Do not use Tailwind arbitrary values",
          "Do not change hex colors to named colors",
          "Do not simplify box-shadow values",
          "Do not add CSS properties that are not in criticalSelectors or in elements[].styles (or element states)",
          "Do not reorder children: follow contentOrder and elements[].children order exactly",
          "Build exactly what is in the spec: structure, styles, and defaultContent from the JSON only; no inference, no additions, no \"fixes\""
        ]
      },
      "elements": [
        {
          "selector": ".btn-group",
          "tag": "div",
          "styles": {}
        }
      ]
    },
    "default-cp-dark-md": {
      "_meta": {
        "theme": "cp",
        "mode": "dark",
        "locked": true
      },
      "_buildContract": {
        "criticalSelectors": {
          ".btn-group": {}
        },
        "forbiddenModifications": [
          "Do not use Tailwind arbitrary values",
          "Do not change hex colors to named colors",
          "Do not simplify box-shadow values",
          "Do not add CSS properties that are not in criticalSelectors or in elements[].styles (or element states)",
          "Do not reorder children: follow contentOrder and elements[].children order exactly",
          "Build exactly what is in the spec: structure, styles, and defaultContent from the JSON only; no inference, no additions, no \"fixes\""
        ]
      },
      "elements": [
        {
          "selector": ".btn-group",
          "tag": "div",
          "styles": {}
        }
      ]
    },
    "default-cp-dark-lg": {
      "_meta": {
        "theme": "cp",
        "mode": "dark",
        "locked": true
      },
      "_buildContract": {
        "criticalSelectors": {
          ".btn-group": {}
        },
        "forbiddenModifications": [
          "Do not use Tailwind arbitrary values",
          "Do not change hex colors to named colors",
          "Do not simplify box-shadow values",
          "Do not add CSS properties that are not in criticalSelectors or in elements[].styles (or element states)",
          "Do not reorder children: follow contentOrder and elements[].children order exactly",
          "Build exactly what is in the spec: structure, styles, and defaultContent from the JSON only; no inference, no additions, no \"fixes\""
        ]
      },
      "elements": [
        {
          "selector": ".btn-group",
          "tag": "div",
          "styles": {}
        }
      ]
    },
    "default-vp-light-sm": {
      "_meta": {
        "theme": "vp",
        "mode": "light",
        "locked": true
      },
      "_buildContract": {
        "criticalSelectors": {
          ".btn-group": {}
        },
        "forbiddenModifications": [
          "Do not use Tailwind arbitrary values",
          "Do not change hex colors to named colors",
          "Do not simplify box-shadow values",
          "Do not add CSS properties that are not in criticalSelectors or in elements[].styles (or element states)",
          "Do not reorder children: follow contentOrder and elements[].children order exactly",
          "Build exactly what is in the spec: structure, styles, and defaultContent from the JSON only; no inference, no additions, no \"fixes\""
        ]
      },
      "elements": [
        {
          "selector": ".btn-group",
          "tag": "div",
          "styles": {}
        }
      ]
    },
    "default-vp-light-md": {
      "_meta": {
        "theme": "vp",
        "mode": "light",
        "locked": true
      },
      "_buildContract": {
        "criticalSelectors": {
          ".btn-group": {}
        },
        "forbiddenModifications": [
          "Do not use Tailwind arbitrary values",
          "Do not change hex colors to named colors",
          "Do not simplify box-shadow values",
          "Do not add CSS properties that are not in criticalSelectors or in elements[].styles (or element states)",
          "Do not reorder children: follow contentOrder and elements[].children order exactly",
          "Build exactly what is in the spec: structure, styles, and defaultContent from the JSON only; no inference, no additions, no \"fixes\""
        ]
      },
      "elements": [
        {
          "selector": ".btn-group",
          "tag": "div",
          "styles": {}
        }
      ]
    },
    "default-vp-light-lg": {
      "_meta": {
        "theme": "vp",
        "mode": "light",
        "locked": true
      },
      "_buildContract": {
        "criticalSelectors": {
          ".btn-group": {}
        },
        "forbiddenModifications": [
          "Do not use Tailwind arbitrary values",
          "Do not change hex colors to named colors",
          "Do not simplify box-shadow values",
          "Do not add CSS properties that are not in criticalSelectors or in elements[].styles (or element states)",
          "Do not reorder children: follow contentOrder and elements[].children order exactly",
          "Build exactly what is in the spec: structure, styles, and defaultContent from the JSON only; no inference, no additions, no \"fixes\""
        ]
      },
      "elements": [
        {
          "selector": ".btn-group",
          "tag": "div",
          "styles": {}
        }
      ]
    },
    "default-vp-dark-sm": {
      "_meta": {
        "theme": "vp",
        "mode": "dark",
        "locked": true
      },
      "_buildContract": {
        "criticalSelectors": {
          ".btn-group": {}
        },
        "forbiddenModifications": [
          "Do not use Tailwind arbitrary values",
          "Do not change hex colors to named colors",
          "Do not simplify box-shadow values",
          "Do not add CSS properties that are not in criticalSelectors or in elements[].styles (or element states)",
          "Do not reorder children: follow contentOrder and elements[].children order exactly",
          "Build exactly what is in the spec: structure, styles, and defaultContent from the JSON only; no inference, no additions, no \"fixes\""
        ]
      },
      "elements": [
        {
          "selector": ".btn-group",
          "tag": "div",
          "styles": {}
        }
      ]
    },
    "default-vp-dark-md": {
      "_meta": {
        "theme": "vp",
        "mode": "dark",
        "locked": true
      },
      "_buildContract": {
        "criticalSelectors": {
          ".btn-group": {}
        },
        "forbiddenModifications": [
          "Do not use Tailwind arbitrary values",
          "Do not change hex colors to named colors",
          "Do not simplify box-shadow values",
          "Do not add CSS properties that are not in criticalSelectors or in elements[].styles (or element states)",
          "Do not reorder children: follow contentOrder and elements[].children order exactly",
          "Build exactly what is in the spec: structure, styles, and defaultContent from the JSON only; no inference, no additions, no \"fixes\""
        ]
      },
      "elements": [
        {
          "selector": ".btn-group",
          "tag": "div",
          "styles": {}
        }
      ]
    },
    "default-vp-dark-lg": {
      "_meta": {
        "theme": "vp",
        "mode": "dark",
        "locked": true
      },
      "_buildContract": {
        "criticalSelectors": {
          ".btn-group": {}
        },
        "forbiddenModifications": [
          "Do not use Tailwind arbitrary values",
          "Do not change hex colors to named colors",
          "Do not simplify box-shadow values",
          "Do not add CSS properties that are not in criticalSelectors or in elements[].styles (or element states)",
          "Do not reorder children: follow contentOrder and elements[].children order exactly",
          "Build exactly what is in the spec: structure, styles, and defaultContent from the JSON only; no inference, no additions, no \"fixes\""
        ]
      },
      "elements": [
        {
          "selector": ".btn-group",
          "tag": "div",
          "styles": {}
        }
      ]
    },
    "default-ppm-light-sm": {
      "_meta": {
        "theme": "ppm",
        "mode": "light",
        "locked": true
      },
      "_buildContract": {
        "criticalSelectors": {
          ".btn-group": {}
        },
        "forbiddenModifications": [
          "Do not use Tailwind arbitrary values",
          "Do not change hex colors to named colors",
          "Do not simplify box-shadow values",
          "Do not add CSS properties that are not in criticalSelectors or in elements[].styles (or element states)",
          "Do not reorder children: follow contentOrder and elements[].children order exactly",
          "Build exactly what is in the spec: structure, styles, and defaultContent from the JSON only; no inference, no additions, no \"fixes\""
        ]
      },
      "elements": [
        {
          "selector": ".btn-group",
          "tag": "div",
          "styles": {}
        }
      ]
    },
    "default-ppm-light-md": {
      "_meta": {
        "theme": "ppm",
        "mode": "light",
        "locked": true
      },
      "_buildContract": {
        "criticalSelectors": {
          ".btn-group": {}
        },
        "forbiddenModifications": [
          "Do not use Tailwind arbitrary values",
          "Do not change hex colors to named colors",
          "Do not simplify box-shadow values",
          "Do not add CSS properties that are not in criticalSelectors or in elements[].styles (or element states)",
          "Do not reorder children: follow contentOrder and elements[].children order exactly",
          "Build exactly what is in the spec: structure, styles, and defaultContent from the JSON only; no inference, no additions, no \"fixes\""
        ]
      },
      "elements": [
        {
          "selector": ".btn-group",
          "tag": "div",
          "styles": {}
        }
      ]
    },
    "default-ppm-light-lg": {
      "_meta": {
        "theme": "ppm",
        "mode": "light",
        "locked": true
      },
      "_buildContract": {
        "criticalSelectors": {
          ".btn-group": {}
        },
        "forbiddenModifications": [
          "Do not use Tailwind arbitrary values",
          "Do not change hex colors to named colors",
          "Do not simplify box-shadow values",
          "Do not add CSS properties that are not in criticalSelectors or in elements[].styles (or element states)",
          "Do not reorder children: follow contentOrder and elements[].children order exactly",
          "Build exactly what is in the spec: structure, styles, and defaultContent from the JSON only; no inference, no additions, no \"fixes\""
        ]
      },
      "elements": [
        {
          "selector": ".btn-group",
          "tag": "div",
          "styles": {}
        }
      ]
    },
    "default-ppm-dark-sm": {
      "_meta": {
        "theme": "ppm",
        "mode": "dark",
        "locked": true
      },
      "_buildContract": {
        "criticalSelectors": {
          ".btn-group": {}
        },
        "forbiddenModifications": [
          "Do not use Tailwind arbitrary values",
          "Do not change hex colors to named colors",
          "Do not simplify box-shadow values",
          "Do not add CSS properties that are not in criticalSelectors or in elements[].styles (or element states)",
          "Do not reorder children: follow contentOrder and elements[].children order exactly",
          "Build exactly what is in the spec: structure, styles, and defaultContent from the JSON only; no inference, no additions, no \"fixes\""
        ]
      },
      "elements": [
        {
          "selector": ".btn-group",
          "tag": "div",
          "styles": {}
        }
      ]
    },
    "default-ppm-dark-md": {
      "_meta": {
        "theme": "ppm",
        "mode": "dark",
        "locked": true
      },
      "_buildContract": {
        "criticalSelectors": {
          ".btn-group": {}
        },
        "forbiddenModifications": [
          "Do not use Tailwind arbitrary values",
          "Do not change hex colors to named colors",
          "Do not simplify box-shadow values",
          "Do not add CSS properties that are not in criticalSelectors or in elements[].styles (or element states)",
          "Do not reorder children: follow contentOrder and elements[].children order exactly",
          "Build exactly what is in the spec: structure, styles, and defaultContent from the JSON only; no inference, no additions, no \"fixes\""
        ]
      },
      "elements": [
        {
          "selector": ".btn-group",
          "tag": "div",
          "styles": {}
        }
      ]
    },
    "default-ppm-dark-lg": {
      "_meta": {
        "theme": "ppm",
        "mode": "dark",
        "locked": true
      },
      "_buildContract": {
        "criticalSelectors": {
          ".btn-group": {}
        },
        "forbiddenModifications": [
          "Do not use Tailwind arbitrary values",
          "Do not change hex colors to named colors",
          "Do not simplify box-shadow values",
          "Do not add CSS properties that are not in criticalSelectors or in elements[].styles (or element states)",
          "Do not reorder children: follow contentOrder and elements[].children order exactly",
          "Build exactly what is in the spec: structure, styles, and defaultContent from the JSON only; no inference, no additions, no \"fixes\""
        ]
      },
      "elements": [
        {
          "selector": ".btn-group",
          "tag": "div",
          "styles": {}
        }
      ]
    },
    "default-maconomy-light-sm": {
      "_meta": {
        "theme": "maconomy",
        "mode": "light",
        "locked": true
      },
      "_buildContract": {
        "criticalSelectors": {
          ".btn-group": {}
        },
        "forbiddenModifications": [
          "Do not use Tailwind arbitrary values",
          "Do not change hex colors to named colors",
          "Do not simplify box-shadow values",
          "Do not add CSS properties that are not in criticalSelectors or in elements[].styles (or element states)",
          "Do not reorder children: follow contentOrder and elements[].children order exactly",
          "Build exactly what is in the spec: structure, styles, and defaultContent from the JSON only; no inference, no additions, no \"fixes\""
        ]
      },
      "elements": [
        {
          "selector": ".btn-group",
          "tag": "div",
          "styles": {}
        }
      ]
    },
    "default-maconomy-light-md": {
      "_meta": {
        "theme": "maconomy",
        "mode": "light",
        "locked": true
      },
      "_buildContract": {
        "criticalSelectors": {
          ".btn-group": {}
        },
        "forbiddenModifications": [
          "Do not use Tailwind arbitrary values",
          "Do not change hex colors to named colors",
          "Do not simplify box-shadow values",
          "Do not add CSS properties that are not in criticalSelectors or in elements[].styles (or element states)",
          "Do not reorder children: follow contentOrder and elements[].children order exactly",
          "Build exactly what is in the spec: structure, styles, and defaultContent from the JSON only; no inference, no additions, no \"fixes\""
        ]
      },
      "elements": [
        {
          "selector": ".btn-group",
          "tag": "div",
          "styles": {}
        }
      ]
    },
    "default-maconomy-light-lg": {
      "_meta": {
        "theme": "maconomy",
        "mode": "light",
        "locked": true
      },
      "_buildContract": {
        "criticalSelectors": {
          ".btn-group": {}
        },
        "forbiddenModifications": [
          "Do not use Tailwind arbitrary values",
          "Do not change hex colors to named colors",
          "Do not simplify box-shadow values",
          "Do not add CSS properties that are not in criticalSelectors or in elements[].styles (or element states)",
          "Do not reorder children: follow contentOrder and elements[].children order exactly",
          "Build exactly what is in the spec: structure, styles, and defaultContent from the JSON only; no inference, no additions, no \"fixes\""
        ]
      },
      "elements": [
        {
          "selector": ".btn-group",
          "tag": "div",
          "styles": {}
        }
      ]
    },
    "default-maconomy-dark-sm": {
      "_meta": {
        "theme": "maconomy",
        "mode": "dark",
        "locked": true
      },
      "_buildContract": {
        "criticalSelectors": {
          ".btn-group": {}
        },
        "forbiddenModifications": [
          "Do not use Tailwind arbitrary values",
          "Do not change hex colors to named colors",
          "Do not simplify box-shadow values",
          "Do not add CSS properties that are not in criticalSelectors or in elements[].styles (or element states)",
          "Do not reorder children: follow contentOrder and elements[].children order exactly",
          "Build exactly what is in the spec: structure, styles, and defaultContent from the JSON only; no inference, no additions, no \"fixes\""
        ]
      },
      "elements": [
        {
          "selector": ".btn-group",
          "tag": "div",
          "styles": {}
        }
      ]
    },
    "default-maconomy-dark-md": {
      "_meta": {
        "theme": "maconomy",
        "mode": "dark",
        "locked": true
      },
      "_buildContract": {
        "criticalSelectors": {
          ".btn-group": {}
        },
        "forbiddenModifications": [
          "Do not use Tailwind arbitrary values",
          "Do not change hex colors to named colors",
          "Do not simplify box-shadow values",
          "Do not add CSS properties that are not in criticalSelectors or in elements[].styles (or element states)",
          "Do not reorder children: follow contentOrder and elements[].children order exactly",
          "Build exactly what is in the spec: structure, styles, and defaultContent from the JSON only; no inference, no additions, no \"fixes\""
        ]
      },
      "elements": [
        {
          "selector": ".btn-group",
          "tag": "div",
          "styles": {}
        }
      ]
    },
    "default-maconomy-dark-lg": {
      "_meta": {
        "theme": "maconomy",
        "mode": "dark",
        "locked": true
      },
      "_buildContract": {
        "criticalSelectors": {
          ".btn-group": {}
        },
        "forbiddenModifications": [
          "Do not use Tailwind arbitrary values",
          "Do not change hex colors to named colors",
          "Do not simplify box-shadow values",
          "Do not add CSS properties that are not in criticalSelectors or in elements[].styles (or element states)",
          "Do not reorder children: follow contentOrder and elements[].children order exactly",
          "Build exactly what is in the spec: structure, styles, and defaultContent from the JSON only; no inference, no additions, no \"fixes\""
        ]
      },
      "elements": [
        {
          "selector": ".btn-group",
          "tag": "div",
          "styles": {}
        }
      ]
    },
    "outline-cp-light-sm": {
      "_meta": {
        "theme": "cp",
        "mode": "light",
        "locked": true
      },
      "_buildContract": {
        "criticalSelectors": {
          ".btn-group": {}
        },
        "forbiddenModifications": [
          "Do not use Tailwind arbitrary values",
          "Do not change hex colors to named colors",
          "Do not simplify box-shadow values",
          "Do not add CSS properties that are not in criticalSelectors or in elements[].styles (or element states)",
          "Do not reorder children: follow contentOrder and elements[].children order exactly",
          "Build exactly what is in the spec: structure, styles, and defaultContent from the JSON only; no inference, no additions, no \"fixes\""
        ]
      },
      "elements": [
        {
          "selector": ".btn-group",
          "tag": "div",
          "styles": {}
        }
      ]
    },
    "outline-cp-light-md": {
      "_meta": {
        "theme": "cp",
        "mode": "light",
        "locked": true
      },
      "_buildContract": {
        "criticalSelectors": {
          ".btn-group": {}
        },
        "forbiddenModifications": [
          "Do not use Tailwind arbitrary values",
          "Do not change hex colors to named colors",
          "Do not simplify box-shadow values",
          "Do not add CSS properties that are not in criticalSelectors or in elements[].styles (or element states)",
          "Do not reorder children: follow contentOrder and elements[].children order exactly",
          "Build exactly what is in the spec: structure, styles, and defaultContent from the JSON only; no inference, no additions, no \"fixes\""
        ]
      },
      "elements": [
        {
          "selector": ".btn-group",
          "tag": "div",
          "styles": {}
        }
      ]
    },
    "outline-cp-light-lg": {
      "_meta": {
        "theme": "cp",
        "mode": "light",
        "locked": true
      },
      "_buildContract": {
        "criticalSelectors": {
          ".btn-group": {}
        },
        "forbiddenModifications": [
          "Do not use Tailwind arbitrary values",
          "Do not change hex colors to named colors",
          "Do not simplify box-shadow values",
          "Do not add CSS properties that are not in criticalSelectors or in elements[].styles (or element states)",
          "Do not reorder children: follow contentOrder and elements[].children order exactly",
          "Build exactly what is in the spec: structure, styles, and defaultContent from the JSON only; no inference, no additions, no \"fixes\""
        ]
      },
      "elements": [
        {
          "selector": ".btn-group",
          "tag": "div",
          "styles": {}
        }
      ]
    },
    "outline-cp-dark-sm": {
      "_meta": {
        "theme": "cp",
        "mode": "dark",
        "locked": true
      },
      "_buildContract": {
        "criticalSelectors": {
          ".btn-group": {}
        },
        "forbiddenModifications": [
          "Do not use Tailwind arbitrary values",
          "Do not change hex colors to named colors",
          "Do not simplify box-shadow values",
          "Do not add CSS properties that are not in criticalSelectors or in elements[].styles (or element states)",
          "Do not reorder children: follow contentOrder and elements[].children order exactly",
          "Build exactly what is in the spec: structure, styles, and defaultContent from the JSON only; no inference, no additions, no \"fixes\""
        ]
      },
      "elements": [
        {
          "selector": ".btn-group",
          "tag": "div",
          "styles": {}
        }
      ]
    },
    "outline-cp-dark-md": {
      "_meta": {
        "theme": "cp",
        "mode": "dark",
        "locked": true
      },
      "_buildContract": {
        "criticalSelectors": {
          ".btn-group": {}
        },
        "forbiddenModifications": [
          "Do not use Tailwind arbitrary values",
          "Do not change hex colors to named colors",
          "Do not simplify box-shadow values",
          "Do not add CSS properties that are not in criticalSelectors or in elements[].styles (or element states)",
          "Do not reorder children: follow contentOrder and elements[].children order exactly",
          "Build exactly what is in the spec: structure, styles, and defaultContent from the JSON only; no inference, no additions, no \"fixes\""
        ]
      },
      "elements": [
        {
          "selector": ".btn-group",
          "tag": "div",
          "styles": {}
        }
      ]
    },
    "outline-cp-dark-lg": {
      "_meta": {
        "theme": "cp",
        "mode": "dark",
        "locked": true
      },
      "_buildContract": {
        "criticalSelectors": {
          ".btn-group": {}
        },
        "forbiddenModifications": [
          "Do not use Tailwind arbitrary values",
          "Do not change hex colors to named colors",
          "Do not simplify box-shadow values",
          "Do not add CSS properties that are not in criticalSelectors or in elements[].styles (or element states)",
          "Do not reorder children: follow contentOrder and elements[].children order exactly",
          "Build exactly what is in the spec: structure, styles, and defaultContent from the JSON only; no inference, no additions, no \"fixes\""
        ]
      },
      "elements": [
        {
          "selector": ".btn-group",
          "tag": "div",
          "styles": {}
        }
      ]
    },
    "outline-vp-light-sm": {
      "_meta": {
        "theme": "vp",
        "mode": "light",
        "locked": true
      },
      "_buildContract": {
        "criticalSelectors": {
          ".btn-group": {}
        },
        "forbiddenModifications": [
          "Do not use Tailwind arbitrary values",
          "Do not change hex colors to named colors",
          "Do not simplify box-shadow values",
          "Do not add CSS properties that are not in criticalSelectors or in elements[].styles (or element states)",
          "Do not reorder children: follow contentOrder and elements[].children order exactly",
          "Build exactly what is in the spec: structure, styles, and defaultContent from the JSON only; no inference, no additions, no \"fixes\""
        ]
      },
      "elements": [
        {
          "selector": ".btn-group",
          "tag": "div",
          "styles": {}
        }
      ]
    },
    "outline-vp-light-md": {
      "_meta": {
        "theme": "vp",
        "mode": "light",
        "locked": true
      },
      "_buildContract": {
        "criticalSelectors": {
          ".btn-group": {}
        },
        "forbiddenModifications": [
          "Do not use Tailwind arbitrary values",
          "Do not change hex colors to named colors",
          "Do not simplify box-shadow values",
          "Do not add CSS properties that are not in criticalSelectors or in elements[].styles (or element states)",
          "Do not reorder children: follow contentOrder and elements[].children order exactly",
          "Build exactly what is in the spec: structure, styles, and defaultContent from the JSON only; no inference, no additions, no \"fixes\""
        ]
      },
      "elements": [
        {
          "selector": ".btn-group",
          "tag": "div",
          "styles": {}
        }
      ]
    },
    "outline-vp-light-lg": {
      "_meta": {
        "theme": "vp",
        "mode": "light",
        "locked": true
      },
      "_buildContract": {
        "criticalSelectors": {
          ".btn-group": {}
        },
        "forbiddenModifications": [
          "Do not use Tailwind arbitrary values",
          "Do not change hex colors to named colors",
          "Do not simplify box-shadow values",
          "Do not add CSS properties that are not in criticalSelectors or in elements[].styles (or element states)",
          "Do not reorder children: follow contentOrder and elements[].children order exactly",
          "Build exactly what is in the spec: structure, styles, and defaultContent from the JSON only; no inference, no additions, no \"fixes\""
        ]
      },
      "elements": [
        {
          "selector": ".btn-group",
          "tag": "div",
          "styles": {}
        }
      ]
    },
    "outline-vp-dark-sm": {
      "_meta": {
        "theme": "vp",
        "mode": "dark",
        "locked": true
      },
      "_buildContract": {
        "criticalSelectors": {
          ".btn-group": {}
        },
        "forbiddenModifications": [
          "Do not use Tailwind arbitrary values",
          "Do not change hex colors to named colors",
          "Do not simplify box-shadow values",
          "Do not add CSS properties that are not in criticalSelectors or in elements[].styles (or element states)",
          "Do not reorder children: follow contentOrder and elements[].children order exactly",
          "Build exactly what is in the spec: structure, styles, and defaultContent from the JSON only; no inference, no additions, no \"fixes\""
        ]
      },
      "elements": [
        {
          "selector": ".btn-group",
          "tag": "div",
          "styles": {}
        }
      ]
    },
    "outline-vp-dark-md": {
      "_meta": {
        "theme": "vp",
        "mode": "dark",
        "locked": true
      },
      "_buildContract": {
        "criticalSelectors": {
          ".btn-group": {}
        },
        "forbiddenModifications": [
          "Do not use Tailwind arbitrary values",
          "Do not change hex colors to named colors",
          "Do not simplify box-shadow values",
          "Do not add CSS properties that are not in criticalSelectors or in elements[].styles (or element states)",
          "Do not reorder children: follow contentOrder and elements[].children order exactly",
          "Build exactly what is in the spec: structure, styles, and defaultContent from the JSON only; no inference, no additions, no \"fixes\""
        ]
      },
      "elements": [
        {
          "selector": ".btn-group",
          "tag": "div",
          "styles": {}
        }
      ]
    },
    "outline-vp-dark-lg": {
      "_meta": {
        "theme": "vp",
        "mode": "dark",
        "locked": true
      },
      "_buildContract": {
        "criticalSelectors": {
          ".btn-group": {}
        },
        "forbiddenModifications": [
          "Do not use Tailwind arbitrary values",
          "Do not change hex colors to named colors",
          "Do not simplify box-shadow values",
          "Do not add CSS properties that are not in criticalSelectors or in elements[].styles (or element states)",
          "Do not reorder children: follow contentOrder and elements[].children order exactly",
          "Build exactly what is in the spec: structure, styles, and defaultContent from the JSON only; no inference, no additions, no \"fixes\""
        ]
      },
      "elements": [
        {
          "selector": ".btn-group",
          "tag": "div",
          "styles": {}
        }
      ]
    },
    "outline-ppm-light-sm": {
      "_meta": {
        "theme": "ppm",
        "mode": "light",
        "locked": true
      },
      "_buildContract": {
        "criticalSelectors": {
          ".btn-group": {}
        },
        "forbiddenModifications": [
          "Do not use Tailwind arbitrary values",
          "Do not change hex colors to named colors",
          "Do not simplify box-shadow values",
          "Do not add CSS properties that are not in criticalSelectors or in elements[].styles (or element states)",
          "Do not reorder children: follow contentOrder and elements[].children order exactly",
          "Build exactly what is in the spec: structure, styles, and defaultContent from the JSON only; no inference, no additions, no \"fixes\""
        ]
      },
      "elements": [
        {
          "selector": ".btn-group",
          "tag": "div",
          "styles": {}
        }
      ]
    },
    "outline-ppm-light-md": {
      "_meta": {
        "theme": "ppm",
        "mode": "light",
        "locked": true
      },
      "_buildContract": {
        "criticalSelectors": {
          ".btn-group": {}
        },
        "forbiddenModifications": [
          "Do not use Tailwind arbitrary values",
          "Do not change hex colors to named colors",
          "Do not simplify box-shadow values",
          "Do not add CSS properties that are not in criticalSelectors or in elements[].styles (or element states)",
          "Do not reorder children: follow contentOrder and elements[].children order exactly",
          "Build exactly what is in the spec: structure, styles, and defaultContent from the JSON only; no inference, no additions, no \"fixes\""
        ]
      },
      "elements": [
        {
          "selector": ".btn-group",
          "tag": "div",
          "styles": {}
        }
      ]
    },
    "outline-ppm-light-lg": {
      "_meta": {
        "theme": "ppm",
        "mode": "light",
        "locked": true
      },
      "_buildContract": {
        "criticalSelectors": {
          ".btn-group": {}
        },
        "forbiddenModifications": [
          "Do not use Tailwind arbitrary values",
          "Do not change hex colors to named colors",
          "Do not simplify box-shadow values",
          "Do not add CSS properties that are not in criticalSelectors or in elements[].styles (or element states)",
          "Do not reorder children: follow contentOrder and elements[].children order exactly",
          "Build exactly what is in the spec: structure, styles, and defaultContent from the JSON only; no inference, no additions, no \"fixes\""
        ]
      },
      "elements": [
        {
          "selector": ".btn-group",
          "tag": "div",
          "styles": {}
        }
      ]
    },
    "outline-ppm-dark-sm": {
      "_meta": {
        "theme": "ppm",
        "mode": "dark",
        "locked": true
      },
      "_buildContract": {
        "criticalSelectors": {
          ".btn-group": {}
        },
        "forbiddenModifications": [
          "Do not use Tailwind arbitrary values",
          "Do not change hex colors to named colors",
          "Do not simplify box-shadow values",
          "Do not add CSS properties that are not in criticalSelectors or in elements[].styles (or element states)",
          "Do not reorder children: follow contentOrder and elements[].children order exactly",
          "Build exactly what is in the spec: structure, styles, and defaultContent from the JSON only; no inference, no additions, no \"fixes\""
        ]
      },
      "elements": [
        {
          "selector": ".btn-group",
          "tag": "div",
          "styles": {}
        }
      ]
    },
    "outline-ppm-dark-md": {
      "_meta": {
        "theme": "ppm",
        "mode": "dark",
        "locked": true
      },
      "_buildContract": {
        "criticalSelectors": {
          ".btn-group": {}
        },
        "forbiddenModifications": [
          "Do not use Tailwind arbitrary values",
          "Do not change hex colors to named colors",
          "Do not simplify box-shadow values",
          "Do not add CSS properties that are not in criticalSelectors or in elements[].styles (or element states)",
          "Do not reorder children: follow contentOrder and elements[].children order exactly",
          "Build exactly what is in the spec: structure, styles, and defaultContent from the JSON only; no inference, no additions, no \"fixes\""
        ]
      },
      "elements": [
        {
          "selector": ".btn-group",
          "tag": "div",
          "styles": {}
        }
      ]
    },
    "outline-ppm-dark-lg": {
      "_meta": {
        "theme": "ppm",
        "mode": "dark",
        "locked": true
      },
      "_buildContract": {
        "criticalSelectors": {
          ".btn-group": {}
        },
        "forbiddenModifications": [
          "Do not use Tailwind arbitrary values",
          "Do not change hex colors to named colors",
          "Do not simplify box-shadow values",
          "Do not add CSS properties that are not in criticalSelectors or in elements[].styles (or element states)",
          "Do not reorder children: follow contentOrder and elements[].children order exactly",
          "Build exactly what is in the spec: structure, styles, and defaultContent from the JSON only; no inference, no additions, no \"fixes\""
        ]
      },
      "elements": [
        {
          "selector": ".btn-group",
          "tag": "div",
          "styles": {}
        }
      ]
    },
    "outline-maconomy-light-sm": {
      "_meta": {
        "theme": "maconomy",
        "mode": "light",
        "locked": true
      },
      "_buildContract": {
        "criticalSelectors": {
          ".btn-group": {}
        },
        "forbiddenModifications": [
          "Do not use Tailwind arbitrary values",
          "Do not change hex colors to named colors",
          "Do not simplify box-shadow values",
          "Do not add CSS properties that are not in criticalSelectors or in elements[].styles (or element states)",
          "Do not reorder children: follow contentOrder and elements[].children order exactly",
          "Build exactly what is in the spec: structure, styles, and defaultContent from the JSON only; no inference, no additions, no \"fixes\""
        ]
      },
      "elements": [
        {
          "selector": ".btn-group",
          "tag": "div",
          "styles": {}
        }
      ]
    },
    "outline-maconomy-light-md": {
      "_meta": {
        "theme": "maconomy",
        "mode": "light",
        "locked": true
      },
      "_buildContract": {
        "criticalSelectors": {
          ".btn-group": {}
        },
        "forbiddenModifications": [
          "Do not use Tailwind arbitrary values",
          "Do not change hex colors to named colors",
          "Do not simplify box-shadow values",
          "Do not add CSS properties that are not in criticalSelectors or in elements[].styles (or element states)",
          "Do not reorder children: follow contentOrder and elements[].children order exactly",
          "Build exactly what is in the spec: structure, styles, and defaultContent from the JSON only; no inference, no additions, no \"fixes\""
        ]
      },
      "elements": [
        {
          "selector": ".btn-group",
          "tag": "div",
          "styles": {}
        }
      ]
    },
    "outline-maconomy-light-lg": {
      "_meta": {
        "theme": "maconomy",
        "mode": "light",
        "locked": true
      },
      "_buildContract": {
        "criticalSelectors": {
          ".btn-group": {}
        },
        "forbiddenModifications": [
          "Do not use Tailwind arbitrary values",
          "Do not change hex colors to named colors",
          "Do not simplify box-shadow values",
          "Do not add CSS properties that are not in criticalSelectors or in elements[].styles (or element states)",
          "Do not reorder children: follow contentOrder and elements[].children order exactly",
          "Build exactly what is in the spec: structure, styles, and defaultContent from the JSON only; no inference, no additions, no \"fixes\""
        ]
      },
      "elements": [
        {
          "selector": ".btn-group",
          "tag": "div",
          "styles": {}
        }
      ]
    },
    "outline-maconomy-dark-sm": {
      "_meta": {
        "theme": "maconomy",
        "mode": "dark",
        "locked": true
      },
      "_buildContract": {
        "criticalSelectors": {
          ".btn-group": {}
        },
        "forbiddenModifications": [
          "Do not use Tailwind arbitrary values",
          "Do not change hex colors to named colors",
          "Do not simplify box-shadow values",
          "Do not add CSS properties that are not in criticalSelectors or in elements[].styles (or element states)",
          "Do not reorder children: follow contentOrder and elements[].children order exactly",
          "Build exactly what is in the spec: structure, styles, and defaultContent from the JSON only; no inference, no additions, no \"fixes\""
        ]
      },
      "elements": [
        {
          "selector": ".btn-group",
          "tag": "div",
          "styles": {}
        }
      ]
    },
    "outline-maconomy-dark-md": {
      "_meta": {
        "theme": "maconomy",
        "mode": "dark",
        "locked": true
      },
      "_buildContract": {
        "criticalSelectors": {
          ".btn-group": {}
        },
        "forbiddenModifications": [
          "Do not use Tailwind arbitrary values",
          "Do not change hex colors to named colors",
          "Do not simplify box-shadow values",
          "Do not add CSS properties that are not in criticalSelectors or in elements[].styles (or element states)",
          "Do not reorder children: follow contentOrder and elements[].children order exactly",
          "Build exactly what is in the spec: structure, styles, and defaultContent from the JSON only; no inference, no additions, no \"fixes\""
        ]
      },
      "elements": [
        {
          "selector": ".btn-group",
          "tag": "div",
          "styles": {}
        }
      ]
    },
    "outline-maconomy-dark-lg": {
      "_meta": {
        "theme": "maconomy",
        "mode": "dark",
        "locked": true
      },
      "_buildContract": {
        "criticalSelectors": {
          ".btn-group": {}
        },
        "forbiddenModifications": [
          "Do not use Tailwind arbitrary values",
          "Do not change hex colors to named colors",
          "Do not simplify box-shadow values",
          "Do not add CSS properties that are not in criticalSelectors or in elements[].styles (or element states)",
          "Do not reorder children: follow contentOrder and elements[].children order exactly",
          "Build exactly what is in the spec: structure, styles, and defaultContent from the JSON only; no inference, no additions, no \"fixes\""
        ]
      },
      "elements": [
        {
          "selector": ".btn-group",
          "tag": "div",
          "styles": {}
        }
      ]
    }
  },
  "guidance": {
    "patterns": {},
    "guidelines": {}
  },
  "specKeyOrder": [
    "variant",
    "theme",
    "mode",
    "size"
  ],
  "dimensionDefaults": {
    "variant": "default",
    "theme": "cp",
    "mode": "light",
    "size": "md"
  },
  "structure": {
    "root": ".button-group",
    "children": []
  },
  "fonts": {
    "Figtree": "https://fonts.googleapis.com/css2?family=Figtree:wght@300..900&display=swap",
    "Lexend": "https://fonts.googleapis.com/css2?family=Lexend:wght@400;500;600;700;800;900&display=swap",
    "JetBrains Mono": "https://fonts.googleapis.com/css2?family=JetBrains+Mono:wght@400;500;600&display=swap"
  },
  "defaultContent": {
    "_rule": "No default content defined; do not invent labels, icons, or copy. Use only what is in the spec or leave slots empty."
  },
  "interactivity": {
    "events": [],
    "state": [
      {
        "name": "—",
        "type": "—",
        "description": "Layout only; wraps buttons. No client state; each button handles its own click."
      }
    ]
  },
  "examples": [
    {
      "name": "Edit and delete actions",
      "description": "Card with edit and delete buttons",
      "recipeId": "card-with-actions"
    },
    {
      "name": "Single action",
      "description": "Card with single view action",
      "recipeId": "card-with-actions"
    },
    {
      "name": "Three actions",
      "description": "Card with view, edit, and delete",
      "recipeId": "card-with-actions"
    },
    {
      "name": "Action group",
      "description": "Standalone button group",
      "snippet": "<ButtonGroup><Button>Save</Button><Button variant=\"ghost\">Cancel</Button></ButtonGroup>"
    }
  ]
}
