{
  "name": "Chip",
  "type": "component",
  "filePath": "src/components/ui/Chip.astro",
  "description": "Chip Component",
  "props": {
    "size": {
      "type": "'sm' | 'md' | 'lg'",
      "optional": true,
      "default": null
    },
    "variant": {
      "type": "'fill' | 'outline'",
      "optional": true,
      "default": null
    },
    "state": {
      "type": "'enabled' | 'disabled' | 'hover' | 'focused' | 'pressed'",
      "optional": true,
      "default": null
    },
    "type": {
      "type": "'chip' | 'horiz-dots' | 'vert-dots' | 'overflow'",
      "optional": true,
      "default": null
    },
    "overflowCount": {
      "type": "number",
      "optional": true,
      "default": null
    },
    "selected": {
      "type": "boolean",
      "optional": true,
      "default": null
    },
    "removable": {
      "type": "boolean",
      "optional": true,
      "default": null
    },
    "icon": {
      "type": "string",
      "optional": true,
      "default": null
    },
    "class": {
      "type": "string",
      "optional": true,
      "default": null
    }
  },
  "imports": {
    "Icon": "./Icon.astro"
  },
  "dependencies": [
    "Icon"
  ],
  "cssClasses": [
    "chip__dots",
    "chip__dots--horiz",
    "chip__dots-svg",
    "chip__dots--vert",
    "chip__overflow-text",
    "chip__remove"
  ],
  "themeSupport": {
    "themes": [
      "cp",
      "vp",
      "ppm",
      "maconomy"
    ],
    "darkMode": true
  },
  "slots": {
    "default": {
      "name": "default",
      "required": true,
      "location": null,
      "description": null,
      "conditional": null
    }
  },
  "structure": {
    "root": {
      "element": "span",
      "class": "classes",
      "spacing": {
        "padding": "0",
        "margin": "0"
      },
      "baseClass": null,
      "modifierClasses": {},
      "children": []
    },
    "children": []
  },
  "_metadata": {
    "lastGenerated": "2026-01-16T19:52:02.818Z",
    "generatedWith": "@astrojs/compiler@2.13.0"
  }
}