{
  "name": "NotificationBadge",
  "type": "component",
  "filePath": "src/components/ui/NotificationBadge.astro",
  "description": "NotificationBadge Component",
  "props": {
    "type": {
      "type": "'dot' | 'number' | 'overflow'",
      "optional": true,
      "default": null
    },
    "size": {
      "type": "'sm' | 'md' | 'lg'",
      "optional": true,
      "default": null
    },
    "variant": {
      "type": "'error' | 'primary'",
      "optional": true,
      "default": null
    },
    "value": {
      "type": "string | number",
      "optional": true,
      "default": null
    },
    "border": {
      "type": "boolean",
      "optional": true,
      "default": null
    },
    "class": {
      "type": "string",
      "optional": true,
      "default": null
    }
  },
  "imports": {},
  "dependencies": [],
  "cssClasses": [],
  "themeSupport": {
    "themes": [
      "cp",
      "vp",
      "ppm",
      "maconomy"
    ],
    "darkMode": true
  },
  "slots": {},
  "structure": {
    "root": {
      "element": "span",
      "class": "classes",
      "spacing": {
        "padding": "0",
        "margin": "0"
      },
      "baseClass": null,
      "modifierClasses": {},
      "children": []
    },
    "children": []
  },
  "_metadata": {
    "lastGenerated": "2026-01-16T19:52:02.901Z",
    "generatedWith": "@astrojs/compiler@2.13.0"
  }
}